scada-tuna/__init__.py
scada-tuna/tuna.py
scada_tuna/__init__.py
scada_tuna/tuna.py
scada_tuna-0.0.3.dist-info/METADATA
scada_tuna-0.0.3.dist-info/WHEEL
scada_tuna-0.0.3.dist-info/top_level.txt
scada_tuna-0.0.3.dist-info/RECORD
