Metadata-Version: 2.1
Name: scada-tuna
Version: 0.0.3
Summary: Generic PLC client
Home-page: https://github.com/aiyojun/scada-tuna
Author: aiyojun
Author-email: aiyojun@gmail.com
License: MIT
Keywords: plc,modbus,mcprotocol
Classifier: Programming Language :: Python :: 3
Requires-Python: >=3.8
Requires-Dist: pymcprotocol==0.3.0
Requires-Dist: pymodbus==3.6.4
